doi_hunter/__init__.py
doi_hunter/__main__.py
doi_hunter/downloader.py
doi_hunter/htmlparser.py
doi_hunter/netinfo.py
doi_hunter/proxy.py
doi_hunter/utils.py
doi_hunter-1.1.0.dist-info/LICENSE.txt
doi_hunter-1.1.0.dist-info/METADATA
doi_hunter-1.1.0.dist-info/WHEEL
doi_hunter-1.1.0.dist-info/entry_points.txt
doi_hunter-1.1.0.dist-info/top_level.txt
doi_hunter-1.1.0.dist-info/RECORD
