Metadata-Version: 2.1
Name: doi-hunter
Version: 1.1.0
Summary: DOI-based paper downloader via Sci-Hub
Home-page: https://github.com/mehmoodulhaq570/DoiHunter
Author: Mehmood Ul Haq
Author-email: Mehmood Ul Haq <mehmoodulhaq1040@gmail.com>
License: MIT
Project-URL: Homepage, https://github.com/mehmoodulhaq570/DoiHunter
Project-URL: Documentation, https://github.com/mehmoodulhaq570/DoiHunter#readme
Project-URL: Source, https://github.com/mehmoodulhaq570/DoiHunter
Project-URL: BugTracker, https://github.com/mehmoodulhaq570/DoiHunter/issues
Keywords: doi,scihub,research,papers,downloader
Requires-Python: >=3.7
License-File: LICENSE.txt
Requires-Dist: requests>=2.25.1
Requires-Dist: beautifulsoup4>=4.9.3
